{"1_pengenalan.qmd":["Sugiyono2018","Creswell2014","Kumar2014","Bazeley2013"],"2_kurikulum.qmd":[],"3_topik.qmd":["Knight2008","Creswell2014","Locke2010","Bazeley2013","Kumar2014"],"4_strukturproposal.qmd":["Creswell2014"],"5_strukturskripsi.qmd":["Tong2007"],"6_teknis.qmd":[],"index.qmd":["Sugiyono2018","Creswell2014","Kumar2014","Bazeley2013","Knight2008","Creswell2014","Locke2010","Bazeley2013","Kumar2014","Creswell2014","Tong2007"],"intro.qmd":[],"judul.qmd":[],"pengenalan.qmd":[],"references.qmd":[],"summary.qmd":[]}
